setup.cfg
setup.py
simpletk/__init__.py
simpletk/main.py
simpletk/widgets.py
simpletk.egg-info/PKG-INFO
simpletk.egg-info/SOURCES.txt
simpletk.egg-info/dependency_links.txt
simpletk.egg-info/not-zip-safe
simpletk.egg-info/top_level.txt