Metadata-Version: 2.1
Name: simpletk
Version: 1.1b1
Summary: Simplified Tkinter module.
Author-email: gigacode7@outlook.com
